iqoptionapi_simple/__init__.py
iqoptionapi_simple-0.0.2.dist-info/METADATA
iqoptionapi_simple-0.0.2.dist-info/WHEEL
iqoptionapi_simple-0.0.2.dist-info/top_level.txt
iqoptionapi_simple-0.0.2.dist-info/RECORD
