Metadata-Version: 2.1
Name: iqoptionapi-simple
Version: 0.0.2
Summary: This api is wrapper for iq option implementation of the iqoption version supported by community.
Home-page: https://github.com/juliansantosinfo/iqoptionapi_simple
Author: Julian de Almeida Santos
Author-email: julian.santos.info@gmail.com
License: GPLv3
Project-URL: Source, https://github.com/juliansantosinfo/iqoptionapi_simple
Keywords: iqoptionapi-simple,iqoptionapi,api
Platform: UNKNOWN
Classifier: Development Status :: 5 - Production/Stable
Classifier: Environment :: Web Environment
Classifier: Intended Audience :: Developers
Classifier: License :: OSI Approved :: GNU General Public License v3 (GPLv3)
Classifier: Operating System :: OS Independent
Classifier: Programming Language :: Python
Classifier: Programming Language :: Python :: 3
Classifier: Programming Language :: Python :: 3 :: Only
Classifier: Programming Language :: Python :: 3.8
Classifier: Programming Language :: Python :: 3.9
Classifier: Topic :: Internet :: WWW/HTTP
Classifier: Topic :: Internet :: WWW/HTTP :: Dynamic Content
Classifier: Topic :: Internet :: WWW/HTTP :: WSGI
Classifier: Topic :: Software Development :: Libraries :: Application Frameworks
Classifier: Topic :: Software Development :: Libraries :: Python Modules
Requires-Python: >=3.8
Requires-Dist: requests
Requires-Dist: websocket-client (==0.56)
Requires-Dist: python-dateutil (==2.8.2)
